PyIRoGlass/BaselineAvgPC.npz
PyIRoGlass/H2Om1635PC.npz
PyIRoGlass/__init__.py
PyIRoGlass/_version.py
PyIRoGlass/core.py
PyIRoGlass/inversion.py
PyIRoGlass/thickness.py
pyiroglass-0.6.6.dist-info/licenses/LICENSE.txt
pyiroglass-0.6.6.dist-info/METADATA
pyiroglass-0.6.6.dist-info/WHEEL
pyiroglass-0.6.6.dist-info/top_level.txt
pyiroglass-0.6.6.dist-info/RECORD
