Metadata-Version: 2.4
Name: pyIRoGlass
Version: 0.6.6
Summary: PyIRoGlass
Home-page: https://github.com/sarahshi/PyIRoGlass
Author: Sarah Shi
Author-email: sarah.c.shi@gmail.com
Classifier: Programming Language :: Python :: 3
Classifier: Operating System :: OS Independent
Requires-Python: >=3.9
License-File: LICENSE.txt
Requires-Dist: pandas
Requires-Dist: numpy
Requires-Dist: matplotlib
Requires-Dist: scikit-learn
Requires-Dist: scipy
Requires-Dist: mc3
Requires-Dist: pykrige
Dynamic: author
Dynamic: author-email
Dynamic: classifier
Dynamic: description
Dynamic: description-content-type
Dynamic: home-page
Dynamic: license-file
Dynamic: requires-dist
Dynamic: requires-python
Dynamic: summary
